apecosm/__init__.py
apecosm/conf.py
apecosm/constants.py
apecosm/domains.py
apecosm/extract.py
apecosm/grid.py
apecosm/habitat.py
apecosm/misc.py
apecosm/mplot.py
apecosm/netcdf.py
apecosm/size_spectra.py
apecosm/ts.py
apecosm-1.0.1.dist-info/LICENSE
apecosm-1.0.1.dist-info/METADATA
apecosm-1.0.1.dist-info/WHEEL
apecosm-1.0.1.dist-info/top_level.txt
apecosm-1.0.1.dist-info/RECORD
